veotos_transform/__init__.py
veotos_transform/command_line.py
veotos_transform/obfuscations.py
veotos_transform-0.1.3.dist-info/METADATA
veotos_transform-0.1.3.dist-info/WHEEL
veotos_transform-0.1.3.dist-info/entry_points.txt
veotos_transform-0.1.3.dist-info/top_level.txt
veotos_transform-0.1.3.dist-info/RECORD
