Metadata-Version: 2.1
Name: veotos-transform
Version: 0.1.3
Summary: Obfuscate text with next consonant or vowel
Home-page: http://github.com/veotos/veotos-transform
Author: veotos
Author-email: veotos@gmail.com
License: GPLv3
Classifier: Programming Language :: Python :: 3.10
Classifier: Topic :: Text Processing :: Linguistic
Classifier: License :: OSI Approved :: GNU General Public License v3 (GPLv3)
Requires-Dist: click
